cli/__init__.py
cli/cli.py
cli/helper/__init__.py
cli/helper/api_helper.py
cli/helper/click_helper.py
traint-0.1.4.dist-info/METADATA
traint-0.1.4.dist-info/WHEEL
traint-0.1.4.dist-info/entry_points.txt
traint-0.1.4.dist-info/top_level.txt
traint-0.1.4.dist-info/RECORD
