Metadata-Version: 2.1
Name: traint
Version: 0.1.4
Summary: traint.ai cli python package
Home-page: https://github.com/heureka-labs/traint
Author: Heureka Labs
Author-email: traint@heureka-labs.de
License: MIT
Platform: UNKNOWN
Classifier: Intended Audience :: Developers
Classifier: Topic :: Scientific/Engineering :: Artificial Intelligence
Classifier: Topic :: Software Development
Classifier: Topic :: Software Development :: Libraries
Classifier: Topic :: Software Development :: Libraries :: Python Modules
Classifier: Programming Language :: Python :: 3
Requires-Dist: click (==7.1.2)
Requires-Dist: pyfiglet (==0.7)
Requires-Dist: requests (==2.24.0)
Requires-Dist: requests-toolbelt
Requires-Dist: tabulate
